pyrmvtxt/__init__.py
pyrmvtxt/rmvtxt_code.py
pyrmvtxt-1.1.4.dist-info/LICENSE.txt
pyrmvtxt-1.1.4.dist-info/METADATA
pyrmvtxt-1.1.4.dist-info/WHEEL
pyrmvtxt-1.1.4.dist-info/top_level.txt
pyrmvtxt-1.1.4.dist-info/RECORD
