Metadata-Version: 2.1
Name: pyrmvtxt
Version: 1.1.4
Summary: Remove text in image
Home-page: UNKNOWN
Author: tasund
Author-email: supakrit.n@hotmail.com
License: MIT License Copyright  2020 TASUNDPermission is hereby granted, free of charge, to any person obtaining a copy of this software and associated documentation files (the Software), to deal in the Software without restriction,including without limitation the rights to use, copy, modify, merge, publish, distribute, sublicense,and/or sell copies of the Software, and to permit persons to whom the Software is furnished to do so, subject to the following conditions: The above copyright notice a
Keywords: removetextfromimage
Platform: UNKNOWN
Requires-Dist: opencv-python
Requires-Dist: keras-ocr
Requires-Dist: pandas
